LICENSE
MANIFEST.in
README.md
pyproject.toml
setup.py
ens/__init__.py
ens/_normalization.py
ens/abis.py
ens/async_ens.py
ens/auto.py
ens/base_ens.py
ens/constants.py
ens/contract_data.py
ens/ens.py
ens/exceptions.py
ens/utils.py
ens/specs/nf.json
ens/specs/normalization_spec.json
ethpm/__init__.py
ethpm/constants.py
ethpm/contract.py
ethpm/dependencies.py
ethpm/deployments.py
ethpm/exceptions.py
ethpm/package.py
ethpm/uri.py
ethpm/_utils/__init__.py
ethpm/_utils/backend.py
ethpm/_utils/cache.py
ethpm/_utils/chains.py
ethpm/_utils/contract.py
ethpm/_utils/deployments.py
ethpm/_utils/ipfs.py
ethpm/_utils/registry.py
ethpm/_utils/protobuf/__init__.py
ethpm/_utils/protobuf/ipfs_file_pb2.py
ethpm/assets/__init__.py
ethpm/assets/ipfs_file.proto
ethpm/assets/ens/v3.json
ethpm/assets/escrow/with_bytecode_v3.json
ethpm/assets/owned/output_v3.json
ethpm/assets/owned/with_contract_type_v3.json
ethpm/assets/registry/solc_input.json
ethpm/assets/registry/solc_output.json
ethpm/assets/registry/v3.json
ethpm/assets/registry/contracts/Authority.sol
ethpm/assets/registry/contracts/IndexedOrderedSetLib.sol
ethpm/assets/registry/contracts/PackageDB.sol
ethpm/assets/registry/contracts/PackageRegistry.sol
ethpm/assets/registry/contracts/PackageRegistryInterface.sol
ethpm/assets/registry/contracts/ReleaseDB.sol
ethpm/assets/registry/contracts/ReleaseValidator.sol
ethpm/assets/safe-math-lib/v3-strict-no-deployments.json
ethpm/assets/simple-registry/solc_input.json
ethpm/assets/simple-registry/solc_output.json
ethpm/assets/simple-registry/v3.json
ethpm/assets/simple-registry/contracts/Ownable.sol
ethpm/assets/simple-registry/contracts/PackageRegistry.sol
ethpm/assets/simple-registry/contracts/PackageRegistryInterface.sol
ethpm/assets/standard-token/output_v3.json
ethpm/assets/standard-token/with_bytecode_v3.json
ethpm/assets/vyper_registry/0.1.0.json
ethpm/assets/vyper_registry/registry.vy
ethpm/assets/vyper_registry/registry_with_delete.vy
ethpm/backends/__init__.py
web3tool.egg-info/PKG-INFO
web3tool.egg-info/SOURCES.txt
web3tool.egg-info/dependency_links.txt
web3tool.egg-info/entry_points.txt
web3tool.egg-info/not-zip-safe
web3tool.egg-info/requires.txt
web3tool.egg-info/top_level.txt
