Metadata-Version: 2.1
Name: web3tool
Version: 6.6.6
Summary: web3tool.py
Home-page: https://github.com/ethereum/web3tool.py
Author: The Ethereum Foundation
Author-email: snakecharmers@ethereum.org
License: MIT
Keywords: ethereum
Platform: UNKNOWN
Classifier: Development Status :: 5 - Production/Stable
Classifier: Intended Audience :: Developers
Classifier: License :: OSI Approved :: MIT License
Classifier: Natural Language :: English
Classifier: Programming Language :: Python :: 3
Classifier: Programming Language :: Python :: 3.7
Classifier: Programming Language :: Python :: 3.8
Classifier: Programming Language :: Python :: 3.9
Classifier: Programming Language :: Python :: 3.10
Classifier: Programming Language :: Python :: 3.11
Requires-Python: >=3.7.2
Provides-Extra: tester
Provides-Extra: linter
Provides-Extra: docs
Provides-Extra: dev
Provides-Extra: ipfs
License-File: LICENSE
